<keyframes>
    <key>
        <px>199.923004150</px>
        <py>-83.287834167</py>
        <pz>-26.531366348</pz>
        <ox>-0.351891607</ox>
        <oy>-0.911931157</oy>
        <oz>-0.150877625</oz>
        <ow>0.147614151</ow>
        <easein>0</easein>
        <easeout>0</easeout>
        <time>00:01:23:073</time>
        <value>0.000000000</value>
    </key>
    <key>
        <px>127.394180298</px>
        <py>127.967391968</py>
        <pz>40.219383240</pz>
        <ox>0.538692772</ox>
        <oy>0.828417301</oy>
        <oz>0.138522267</oz>
        <ow>-0.065927170</ow>
        <easein>0</easein>
        <easeout>0</easeout>
        <time>00:01:38:438</time>
        <value>0.000000000</value>
    </key>
</keyframes>
